MLsuite/MLArguments.py
MLsuite/MLEstimators.py
MLsuite/MLLogging.py
MLsuite/MLOpenWrite.py
MLsuite/MLPipeline.py
MLsuite/MLPredicting.py
MLsuite/MLSupervising.py
MLsuite/MLUtilities.py
MLsuite/__init__.py
MLsuite/main.py
mlsuite-2.1.7.data/scripts/mlsuite.py
mlsuite-2.1.7.dist-info/LICENSE
mlsuite-2.1.7.dist-info/METADATA
mlsuite-2.1.7.dist-info/WHEEL
mlsuite-2.1.7.dist-info/top_level.txt
mlsuite-2.1.7.dist-info/RECORD
