Metadata-Version: 2.1
Name: mlsuite
Version: 2.1.7
Summary: The traditional machine learning analysis based on sklearn package
Home-page: https://git.genecast.com.cn/narwhal/mlsuite
Author: suxing li
Author-email: li.suxing@genecast.com.cn
Maintainer: suxing li
Maintainer-email: li.suxing@genecast.com.cn
Platform: all
Classifier: Development Status :: 4 - Beta
Classifier: Environment :: Console
Classifier: Intended Audience :: Science/Research
Classifier: Intended Audience :: Healthcare Industry
Classifier: License :: OSI Approved :: Apache Software License
Classifier: Operating System :: MacOS :: MacOS X
Classifier: Operating System :: POSIX
Classifier: Operating System :: POSIX :: Linux
Classifier: Operating System :: Unix
Classifier: Programming Language :: Python
Classifier: Programming Language :: Python :: 3
Classifier: Programming Language :: Python :: 3.6
Classifier: Programming Language :: Python :: 3.7
Classifier: Programming Language :: Python :: 3.8
Classifier: Programming Language :: Python :: 3.9
Classifier: Topic :: Scientific/Engineering
Classifier: Topic :: Scientific/Engineering :: Bio-Informatics
Classifier: Topic :: Scientific/Engineering :: Medical Science Apps.
Classifier: Topic :: Scientific/Engineering :: Visualization
License-File: LICENSE
Requires-Dist: lightgbm (==3.3.3)
Requires-Dist: joblib (==1.2.0)
Requires-Dist: numpy (==1.21.4)
Requires-Dist: pandas (==1.1.5)
Requires-Dist: scikit-learn (==1.2.0)
Requires-Dist: sklearn-pandas (==2.2.0)
Requires-Dist: xgboost (==1.7.2)
